AUTHORS.rst
CONTRIBUTING.rst
HISTORY.rst
LICENSE
MANIFEST.in
README.rst
setup.cfg
setup.py
docs/Makefile
docs/authors.rst
docs/conf.py
docs/contributing.rst
docs/history.rst
docs/index.rst
docs/installation.rst
docs/make.bat
docs/modules.rst
docs/qarrayrun.rst
docs/readme.rst
docs/usage.rst
qarrayrun/__init__.py
qarrayrun/cli.py
qarrayrun/qarrayrun.py
qarrayrun.egg-info/PKG-INFO
qarrayrun.egg-info/SOURCES.txt
qarrayrun.egg-info/dependency_links.txt
qarrayrun.egg-info/entry_points.txt
qarrayrun.egg-info/not-zip-safe
qarrayrun.egg-info/top_level.txt
tests/__init__.py
tests/test_cli.py
tests/test_qarrayrun.py