Metadata-Version: 1.1
Name: qarrayrun
Version: 1.1.0
Summary: A helper tool for running array jobs on an HPC computational node.
Home-page: https://github.com/CFSAN-Biostatistics/qarrayrun
Author: Steve Davis
Author-email: steven.davis@fda.hhs.gov
License: BSD
Keywords: bioinformatics,NGS,qarrayrun
Platform: UNKNOWN
Classifier: Development Status :: 5 - Production/Stable
Classifier: Intended Audience :: Developers
Classifier: License :: OSI Approved :: BSD License
Classifier: Natural Language :: English
Classifier: Programming Language :: Python :: 2
Classifier: Programming Language :: Python :: 2.7
Classifier: Programming Language :: Python :: 3
Classifier: Programming Language :: Python :: 3.3
Classifier: Programming Language :: Python :: 3.4
Classifier: Programming Language :: Python :: 3.5
Classifier: Programming Language :: Python :: 3.6
